cloudwatch.py
parameters.py
aws_butler-0.1.2.dist-info/METADATA
aws_butler-0.1.2.dist-info/WHEEL
aws_butler-0.1.2.dist-info/entry_points.txt
aws_butler-0.1.2.dist-info/top_level.txt
aws_butler-0.1.2.dist-info/RECORD
